setup.py
symcopy
symcopy/__init__.py
symcopy/symcopy.py
symcopy.egg-info/PKG-INFO
symcopy.egg-info/SOURCES.txt
symcopy.egg-info/dependency_links.txt
symcopy.egg-info/top_level.txt