Metadata-Version: 1.0
Name: symcopy
Version: 0.1
Summary: A package for symbolicly copying directories
Home-page: http://github.com/secsandcyber/symcopy
Author: Matthew Molyett
Author-email: matthewmolyett@gmail.com
License: UNKNOWN
Platform: UNKNOWN
